grandos/__init__.py
grandos-0.0.1.dist-info/METADATA
grandos-0.0.1.dist-info/WHEEL
grandos-0.0.1.dist-info/top_level.txt
grandos-0.0.1.dist-info/RECORD
