Metadata-Version: 2.4
Name: grandos
Version: 0.0.1
Summary: Coming soon.
License: MIT
Requires-Python: >=3.8
